peavy
