Metadata-Version: 1.0
Name: django-peavy
Version: 0.8.5
Summary: 
